{"examples":[{"description":"returns the factorial of the number passed in","full_description":"#factorial returns the factorial of the number passed in","status":"passed","file_path":"./spec/project_euler_factorial_digit_sum_spec.rb","line_number":4,"run_time":0.001611},{"description":"returns the sum of the digits of the number passed in","full_description":"#sum_of_digits returns the sum of the digits of the number passed in","status":"passed","file_path":"./spec/project_euler_factorial_digit_sum_spec.rb","line_number":10,"run_time":4.5e-05},{"description":"returns the sum of the digits of the factorial of the number passed in","full_description":"#factorial_digit_sum returns the sum of the digits of the factorial of the number passed in","status":"passed","file_path":"./spec/project_euler_factorial_digit_sum_spec.rb","line_number":19,"run_time":0.000108}],"summary":{"duration":0.002191,"example_count":3,"failure_count":0,"pending_count":0},"summary_line":"3 examples, 0 failures"}